{
    "BCN3D Cura": {
        "Windows": {
            "major": 2,
            "minor": 0,
            "revision": 2,
            "url": "https://www.bcn3dtechnologies.com/en/3d-printer/bcn3d-cura/"
        },
        "Linux": {
            "major": 2,
            "minor": 0,
            "revision": 2,
            "url": "https://www.bcn3dtechnologies.com/en/3d-printer/bcn3d-cura/"
        },
        "Darwin": {
            "major": 2,
            "minor": 0,
            "revision": 2,
            "url": "https://www.bcn3dtechnologies.com/en/3d-printer/bcn3d-cura/"
        }
    }
}